hggit/__init__.py
hggit/__version__.py
hggit/_ssh.py
hggit/commands.py
hggit/compat.py
hggit/config.py
hggit/debugcommands.py
hggit/git2hg.py
hggit/git_handler.py
hggit/gitdirstate.py
hggit/gitrepo.py
hggit/hg2git.py
hggit/hgrepo.py
hggit/overlay.py
hggit/revsets.py
hggit/schemes.py
hggit/templates.py
hggit/util.py
hggit/verify.py
hggit/helptext/__init__.py
hggit/helptext/config.rst
hg_git-1.1.4.dist-info/COPYING
hg_git-1.1.4.dist-info/METADATA
hg_git-1.1.4.dist-info/WHEEL
hg_git-1.1.4.dist-info/top_level.txt
hg_git-1.1.4.dist-info/RECORD
