Metadata-Version: 2.1
Name: hg-git
Version: 1.1.4
Summary: push to and pull from a Git repository using Mercurial
Home-page: http://foss.heptapod.net/mercurial/hg-git
Author: Scott Chacon, Augie Fackler, Kevin Bullock and others
Maintainer: The hg-git maintainers
Maintainer-email: hg-git@googlegroups.com
License: GPLv2
Keywords: hg git mercurial
Requires-Python: >=3.8
License-File: COPYING
Requires-Dist: dulwich<0.23.0,>=0.20.11
